app/__init__.py
app/__main__.py
app/analyzer.py
app/parser.py
dockcheck-0.1.1.dist-info/licenses/LICENSE
dockcheck-0.1.1.dist-info/METADATA
dockcheck-0.1.1.dist-info/WHEEL
dockcheck-0.1.1.dist-info/entry_points.txt
dockcheck-0.1.1.dist-info/top_level.txt
dockcheck-0.1.1.dist-info/RECORD
