Metadata-Version: 2.4
Name: dockcheck
Version: 0.1.1
Summary: Your Dockerfile's best friend: analyze, lint, and optimize with ease.
Author-email: Rajesh <rajesh@hyperoot.dev>
License: MIT
Classifier: Programming Language :: Python :: 3
Classifier: Programming Language :: Python :: 3.10
Classifier: Programming Language :: Python :: 3.11
Classifier: License :: OSI Approved :: MIT License
Classifier: Operating System :: OS Independent
Classifier: Intended Audience :: Developers
Classifier: Topic :: Software Development :: Build Tools
Requires-Python: >=3.10
License-File: LICENSE
Requires-Dist: typer>=0.15.4
Provides-Extra: dev
Requires-Dist: pre-commit>=4.2.0; extra == "dev"
Requires-Dist: pytest>=8.3.5; extra == "dev"
Requires-Dist: ruff>=0.11.10; extra == "dev"
Requires-Dist: bumpver>=2023.1129; extra == "dev"
Dynamic: license-file
